README.md
setup.py
differentiable_sorting/__init__.py
differentiable_sorting/bitonic_loops.py
differentiable_sorting/differentiable_sorting.py
differentiable_sorting.egg-info/PKG-INFO
differentiable_sorting.egg-info/SOURCES.txt
differentiable_sorting.egg-info/dependency_links.txt
differentiable_sorting.egg-info/top_level.txt
differentiable_sorting/tensorflow/__init__.py
differentiable_sorting/torch/__init__.py
differentiable_sorting/torch/differentiable_sorting_torch.py