Metadata-Version: 2.1
Name: differentiable-sorting
Version: 0.0.3
Summary: Differentiable approximate sorting/argsorting with bitonic networks
Home-page: https://github.com/johnhw/differentiable_sorting
Author: John H Williamson
Author-email: johnhw@gmail.com
License: UNKNOWN
Download-URL: https://github.com/johnhw/differentiable_sorting/tarball/0.1
Keywords: sorting,differentiable,autograd,sort,bitonic
Platform: UNKNOWN
